waifu_vts_controller/audio/controller.py
waifu_vts_controller/audio/utils.py
waifu_vts_controller/controller.py
aiwaifu_vts_controller-1.0.0.dist-info/METADATA
aiwaifu_vts_controller-1.0.0.dist-info/WHEEL
aiwaifu_vts_controller-1.0.0.dist-info/RECORD
