Metadata-Version: 2.1
Name: aiwaifu-vts-controller
Version: 1.0.0
Summary: 
License: MIT
Author: hrnph
Author-email: hrnph@protomail.com
Requires-Python: >=3.10,<4.0
Classifier: License :: OSI Approved :: MIT License
Classifier: Programming Language :: Python :: 3
Classifier: Programming Language :: Python :: 3.10
Classifier: Programming Language :: Python :: 3.11
Classifier: Programming Language :: Python :: 3.12
Requires-Dist: asyncio (>=3.4.3,<4.0.0)
Requires-Dist: fastdtw (>=0.3.4,<0.4.0)
Requires-Dist: librosa (>=0.10.2.post1,<0.11.0)
Requires-Dist: numpy (>=2.0.1,<3.0.0)
Requires-Dist: pyvts (>=0.3.2,<0.4.0)
Requires-Dist: requests (>=2.32.3,<3.0.0)
Requires-Dist: scipy (>=1.14.0,<2.0.0)
Requires-Dist: soundcard (>=0.4.3,<0.5.0)
Requires-Dist: soundfile (>=0.12.1,<0.13.0)
Requires-Dist: websocket-client (>=1.8.0,<2.0.0)
